{
  "Arrow-1": {
    "Arrow-1": {
      "name": "Arrow-1",
      "x": 0,
      "y": 0,
      "width": 157,
      "height": 153,
      "pivotX": -0.3,
      "pivotY": 153.95
    },
    "Arrow-1-note": {
      "name": "Arrow-1-note",
      "x": 622,
      "y": 0,
      "width": 157,
      "height": 154,
      "pivotX": 0,
      "pivotY": 0
    },
    "Arrow-1-hold-end": {
      "name": "Arrow-1-hold-end",
      "x": 779,
      "y": 0,
      "width": 50,
      "height": 64,
      "pivotX": 0,
      "pivotY": 0
    },
    "Arrow-1-hold-piece": {
      "name": "Arrow-1-hold-piece",
      "x": 829,
      "y": 0,
      "width": 50,
      "height": 44,
      "pivotX": 0,
      "pivotY": 0
    },
    "Arrow-1-press-0": {
      "name": "Arrow-1-press-0",
      "x": 879,
      "y": 0,
      "width": 204,
      "height": 201,
      "pivotX": 31.15,
      "pivotY": 37.3,
      "frameX": -17,
      "frameY": -17,
      "frameWidth": 238,
      "frameHeight": 235
    },
    "Arrow-1-press-1": {
      "name": "Arrow-1-press-1",
      "x": 1083,
      "y": 0,
      "width": 238,
      "height": 235
    },
    "Arrow-1-press-2": {
      "name": "Arrow-1-press-2",
      "x": 1321,
      "y": 0,
      "width": 220,
      "height": 217,
      "frameX": -6,
      "frameY": -12,
      "frameWidth": 238,
      "frameHeight": 235
    },
    "Arrow-1-press-0-no": {
      "name": "Arrow-1-press-0-no",
      "x": 1541,
      "y": 0,
      "width": 142,
      "height": 140,
      "pivotX": 0,
      "pivotY": 0,
      "frameX": -4,
      "frameY": -2,
      "frameWidth": 149,
      "frameHeight": 146
    },
    "Arrow-1-press-1-no": {
      "name": "Arrow-1-press-1-no",
      "x": 1541,
      "y": 0,
      "width": 142,
      "height": 140,
      "frameX": -4,
      "frameY": -2,
      "frameWidth": 149,
      "frameHeight": 146
    },
    "Arrow-1-press-2-no": {
      "name": "Arrow-1-press-2-no",
      "x": 1683,
      "y": 0,
      "width": 149,
      "height": 146
    }
  },
  "Arrow-0": {
    "Arrow-0": {
      "name": "Arrow-0",
      "x": 157,
      "y": 0,
      "width": 154,
      "height": 156,
      "pivotX": -0.35,
      "pivotY": 156.85
    },
    "Arrow-0-press-0": {
      "name": "Arrow-0-press-0",
      "x": 50,
      "y": 235,
      "width": 240,
      "height": 239,
      "pivotX": 43.65,
      "pivotY": 31
    },
    "Arrow-0-press-1": {
      "name": "Arrow-0-press-1",
      "x": 290,
      "y": 235,
      "width": 234,
      "height": 238,
      "frameX": 0,
      "frameY": -1,
      "frameWidth": 240,
      "frameHeight": 239
    },
    "Arrow-0-press-2": {
      "name": "Arrow-0-press-2",
      "x": 524,
      "y": 235,
      "width": 220,
      "height": 224,
      "frameX": -7,
      "frameY": -9,
      "frameWidth": 240,
      "frameHeight": 239
    },
    "Arrow-0-press-0-no": {
      "name": "Arrow-0-press-0-no",
      "x": 744,
      "y": 235,
      "width": 140,
      "height": 142,
      "pivotX": 0,
      "pivotY": 0,
      "frameX": -3,
      "frameY": -3,
      "frameWidth": 146,
      "frameHeight": 149
    },
    "Arrow-0-press-1-no": {
      "name": "Arrow-0-press-1-no",
      "x": 744,
      "y": 235,
      "width": 140,
      "height": 142,
      "frameX": -3,
      "frameY": -3,
      "frameWidth": 146,
      "frameHeight": 149
    },
    "Arrow-0-press-2-no": {
      "name": "Arrow-0-press-2-no",
      "x": 884,
      "y": 235,
      "width": 146,
      "height": 149
    },
    "Arrow-0-hold-end": {
      "name": "Arrow-0-hold-end",
      "x": 1030,
      "y": 235,
      "width": 50,
      "height": 64,
      "pivotX": 0,
      "pivotY": 0.3
    },
    "Arrow-0-note": {
      "name": "Arrow-0-note",
      "x": 1080,
      "y": 235,
      "width": 154,
      "height": 157,
      "pivotX": 0,
      "pivotY": 0
    },
    "Arrow-0-hold-piece": {
      "name": "Arrow-0-hold-piece",
      "x": 1234,
      "y": 235,
      "width": 50,
      "height": 44,
      "pivotX": 0,
      "pivotY": 0
    }
  },
  "Arrow-3": {
    "Arrow-3": {
      "name": "Arrow-3",
      "x": 311,
      "y": 0,
      "width": 154,
      "height": 156,
      "pivotX": -0.05,
      "pivotY": 156.6
    },
    "Arrow-3-note": {
      "name": "Arrow-3-note",
      "x": 1284,
      "y": 235,
      "width": 154,
      "height": 157,
      "pivotX": 0,
      "pivotY": 0
    },
    "Arrow-3-hold-end": {
      "name": "Arrow-3-hold-end",
      "x": 1438,
      "y": 235,
      "width": 50,
      "height": 64,
      "pivotX": 0,
      "pivotY": 0
    },
    "Arrow-3-hold-piece": {
      "name": "Arrow-3-hold-piece",
      "x": 1488,
      "y": 235,
      "width": 50,
      "height": 44,
      "pivotX": 0,
      "pivotY": 0
    },
    "Arrow-3-press-0": {
      "name": "Arrow-3-press-0",
      "x": 1538,
      "y": 235,
      "width": 195,
      "height": 198,
      "pivotX": 30.9,
      "pivotY": 31,
      "frameX": -15,
      "frameY": -17,
      "frameWidth": 226,
      "frameHeight": 230
    },
    "Arrow-3-press-1": {
      "name": "Arrow-3-press-1",
      "x": 1733,
      "y": 235,
      "width": 223,
      "height": 226,
      "frameX": -1,
      "frameY": -3,
      "frameWidth": 226,
      "frameHeight": 230
    },
    "Arrow-3-press-2": {
      "name": "Arrow-3-press-2",
      "x": 0,
      "y": 474,
      "width": 226,
      "height": 230
    },
    "Arrow-3-press-0-no": {
      "name": "Arrow-3-press-0-no",
      "x": 226,
      "y": 474,
      "width": 138,
      "height": 141,
      "pivotX": 0,
      "pivotY": 0,
      "frameX": -3,
      "frameY": -7,
      "frameWidth": 148,
      "frameHeight": 151
    },
    "Arrow-3-press-1-no": {
      "name": "Arrow-3-press-1-no",
      "x": 226,
      "y": 474,
      "width": 138,
      "height": 141,
      "frameX": -3,
      "frameY": -7,
      "frameWidth": 148,
      "frameHeight": 151
    },
    "Arrow-3-press-2-no": {
      "name": "Arrow-3-press-2-no",
      "x": 364,
      "y": 474,
      "width": 148,
      "height": 151
    }
  },
  "Arrow-2": {
    "Arrow-2": {
      "name": "Arrow-2",
      "x": 465,
      "y": 0,
      "width": 157,
      "height": 153,
      "pivotX": 0,
      "pivotY": 153.55
    },
    "Arrow-2-note": {
      "name": "Arrow-2-note",
      "x": 1832,
      "y": 0,
      "width": 157,
      "height": 154,
      "pivotX": 0,
      "pivotY": 0
    },
    "Arrow-2-hold-end": {
      "name": "Arrow-2-hold-end",
      "x": 1989,
      "y": 0,
      "width": 50,
      "height": 64,
      "pivotX": 0,
      "pivotY": 0
    },
    "Arrow-2-hold-piece": {
      "name": "Arrow-2-hold-piece",
      "x": 0,
      "y": 235,
      "width": 50,
      "height": 44,
      "pivotX": 0,
      "pivotY": 0
    },
    "Arrow-2-press-0": {
      "name": "Arrow-2-press-0",
      "x": 512,
      "y": 474,
      "width": 198,
      "height": 194,
      "pivotX": 35,
      "pivotY": 34.95,
      "frameX": -19,
      "frameY": -19,
      "frameWidth": 236,
      "frameHeight": 232
    },
    "Arrow-2-press-1": {
      "name": "Arrow-2-press-1",
      "x": 710,
      "y": 474,
      "width": 236,
      "height": 232
    },
    "Arrow-2-press-2": {
      "name": "Arrow-2-press-2",
      "x": 946,
      "y": 474,
      "width": 214,
      "height": 211,
      "frameX": -11,
      "frameY": -10,
      "frameWidth": 236,
      "frameHeight": 232
    },
    "Arrow-2-press-0-no": {
      "name": "Arrow-2-press-0-no",
      "x": 1160,
      "y": 474,
      "width": 144,
      "height": 141,
      "pivotX": 0,
      "pivotY": 0,
      "frameX": -5,
      "frameY": -4,
      "frameWidth": 153,
      "frameHeight": 150
    },
    "Arrow-2-press-1-no": {
      "name": "Arrow-2-press-1-no",
      "x": 1160,
      "y": 474,
      "width": 144,
      "height": 141,
      "frameX": -5,
      "frameY": -4,
      "frameWidth": 153,
      "frameHeight": 150
    },
    "Arrow-2-press-2-no": {
      "name": "Arrow-2-press-2-no",
      "x": 1304,
      "y": 474,
      "width": 153,
      "height": 150
    }
  }
}